nodepy/__init__.py
nodepy/convergence.py
nodepy/downwind_runge_kutta_method.py
nodepy/general_linear_method.py
nodepy/graph.py
nodepy/ivp.py
nodepy/linear_multistep_method.py
nodepy/loadmethod.py
nodepy/low_storage_rk.py
nodepy/oc_butcher.py
nodepy/oc_butcher_high_order.py
nodepy/ode_solver.py
nodepy/rk_master.py
nodepy/rooted_trees.py
nodepy/runge_kutta_method.py
nodepy/semidisc.py
nodepy/snp.py
nodepy/stability_function.py
nodepy/strmanip.py
nodepy/twostep_runge_kutta_method.py
nodepy/unit_tests.py
nodepy/utils.py
nodepy-1.0.1.dist-info/LICENSE.txt
nodepy-1.0.1.dist-info/METADATA
nodepy-1.0.1.dist-info/WHEEL
nodepy-1.0.1.dist-info/top_level.txt
nodepy-1.0.1.dist-info/RECORD
