Metadata-Version: 2.1
Name: nodepy
Version: 1.0.1
Summary: Numerical ODE solvers in Python
Home-page: https://github.com/ketch/nodepy
Author: ['David Ketcheson']
Author-email: dketch@gmail.com
License: modified BSD
Platform: UNKNOWN
Requires-Dist: numpy
Requires-Dist: sympy
Requires-Dist: matplotlib
